{
  "ACL1": 7000,
  "APF2": 10000,
  "CC02": 6500,
  "CC04": 3500,
  "CC12": 6000,
  "FM3U": 2000,
  "IBW0": 1000,
  "IBW1": 1000,
  "ICC00": 2000,
  "ICW00": 2000,
  "IN3BW": 1000,
  "IN3PW": 1000,
  "INB3C": 1500,
  "INBC3W": 1500,
  "INBCW": 1500,
  "INBFW": 1500,
  "INBPC": 1500,
  "INLFC": 1500,
  "INLFP": 1500,
  "INYPW": 1000,
  "IPW0": 1000,
  "IPW1": 1000,
  "IWW00": 2000,
  "MT301": 2490,
  "MT302": 8900,
  "MT303": 11490,
  "MT304": 21990,
  "MT305": 3900,
  "MT308": 2490,
  "MT310": 12490,
  "MT311": 21990,
  "MT314": 2490,
  "MT315": 13990,
  "MT317": 20990,
  "MT321": 11990,
  "MT337": 4990,
  "MTS06": 20000,
  "MTS08": 20000,
  "MTS10": 25000,
  "MTS11": 65000,
  "MTX03": 10000,
  "MTX04": 20000,
  "MTX05": 10000,
  "MTX06": 20000,
  "MTX07": 10000,
  "MTX08": 20000,
  "MTY04": 23000,
  "MTY11": 18700,
  "PBSB": 1000,
  "PMBL": 2000,
  "PMNG": 1000,
  "PMSS": 1500,
  "PPMR": 2000,
  "PPSB": 1000,
  "RFP2": 2000,
  "STY7S": 4000,
  "W39B": 1500,
  "W41B": 1500,
  "WS10": 4500,
  "WTAB": 4500,
  "WTDS": 1500,
  "WTSC": 2000,
  "WTSD": 2000,
  "WTTC": 4500,
  "WTUT": 5500
}
